setup.py
kiss/__init__.py
kiss.py.egg-info/PKG-INFO
kiss.py.egg-info/SOURCES.txt
kiss.py.egg-info/dependency_links.txt
kiss.py.egg-info/requires.txt
kiss.py.egg-info/top_level.txt
kiss/controllers/__init__.py
kiss/controllers/auth.py
kiss/controllers/core.py
kiss/controllers/page.py
kiss/controllers/rest.py
kiss/controllers/router.py
kiss/core/__init__.py
kiss/core/application.py
kiss/core/events.py
kiss/models/__init__.py
kiss/views/__init__.py
kiss/views/core.py
kiss/views/static.py
kiss/views/templates.py