Metadata-Version: 1.1
Name: kiss.py
Version: 0.4.16
Summary: MVC web framework in Python with Gevent, Jinja2, Werkzeug
Home-page: http://stanislavfeldman.github.com/kiss.py/
Author: Stanislav Feldman
Author-email: UNKNOWN
License: UNKNOWN
Keywords: web framework gevent jinja2 werkzeug orm oauth socialauth vkontakte facebook google yandex
Platform: UNKNOWN
Classifier: Development Status :: 5 - Production/Stable
Classifier: Topic :: Software Development
Classifier: Topic :: Software Development :: Libraries :: Application Frameworks
